setup.py
ae_probability/Binomialdistribution.py
ae_probability/Gaussiandistribution.py
ae_probability/Generaldistribution.py
ae_probability/__init__.py
ae_probability.egg-info/PKG-INFO
ae_probability.egg-info/SOURCES.txt
ae_probability.egg-info/dependency_links.txt
ae_probability.egg-info/not-zip-safe
ae_probability.egg-info/top_level.txt