Metadata-Version: 1.0
Name: ae-probability
Version: 1.0
Summary: Gaussian and Binomial distributions
Home-page: UNKNOWN
Author: UNKNOWN
Author-email: aallpererdem@gmail.com
License: UNKNOWN
Platform: UNKNOWN
